pyxreader/__init__.py
pyxreader/_defaults.py
pyxreader/adaptable.py
pyxreader/py.typed
pyxreader/textreader.py
pyxreader/iterators/__init__.py
pyxreader/iterators/base.py
pyxreader/iterators/pdf_iterator.py
pyxreader-0.0.1.dist-info/METADATA
pyxreader-0.0.1.dist-info/WHEEL
pyxreader-0.0.1.dist-info/top_level.txt
pyxreader-0.0.1.dist-info/RECORD
