Metadata-Version: 2.1
Name: pyxreader
Version: 0.0.1
Summary: A versatile module providing memory-efficient text-to-speech capabilities for various file formats.
Home-page: https://github.com/AshGw/pyxreader.git
Author: ashgw
Author-email: AshrefGw@proton.me
Classifier: Programming Language :: Python :: 3.10
Requires-Python: >=3.10
Requires-Dist: pypdf ==3.17.1
Requires-Dist: pyttsx3 ==2.90
